Metadata-Version: 1.2
Name: depoison
Version: 1.0
Summary: Fixes poisoned directories in google cloud buckets
Home-page: https://github.com/EleutherAI/depoison/
Author: Sid Black
License: UNKNOWN
Download-URL: https://github.com/EleutherAI/depoison/archive/1.0.tar.gz
Platform: UNKNOWN
Requires-Python: >=3.5
